quantlab/__init__.py
quantlab/_version.py
quantlab/build_handler.py
quantlab/commands.py
quantlab/extension.py
quantlab/process.py
quantlab/process_app.py
quantlab/qlpmapp.py
quantlab/quantlabapp.py
quantlab/quantlabextensions.py
quantlab/quantlabhubapp.py
quantlab/selenium_check.py
quantlab/semver.py
quantlab/update.py
quantlab/schemas/@quantlab/apputils-extension/package.json
quantlab/schemas/@quantlab/apputils-extension/themes.json
quantlab/schemas/@quantlab/calendar-extension/calendar.json
quantlab/schemas/@quantlab/calendar-extension/jupyter.extensions.calendar.json
quantlab/schemas/@quantlab/calendar-extension/package.json
quantlab/schemas/@quantlab/codemirror-extension/commands.json
quantlab/schemas/@quantlab/codemirror-extension/package.json
quantlab/schemas/@quantlab/fileeditor-extension/package.json
quantlab/schemas/@quantlab/fileeditor-extension/plugin.json
quantlab/schemas/@quantlab/highcharts-extension/highcharts.json
quantlab/schemas/@quantlab/highcharts-extension/jupyter.extensions.highcharts.json
quantlab/schemas/@quantlab/highcharts-extension/package.json
quantlab/schemas/@quantlab/shortcuts-extension/package.json
quantlab/schemas/@quantlab/shortcuts-extension/plugin.json
quantlab/schemas/@quantlab/spreadsheet-extension/jupyter.extensions.spreadsheet.json
quantlab/schemas/@quantlab/spreadsheet-extension/package.json
quantlab/schemas/@quantlab/spreadsheet-extension/spreadsheet.json
quantlab/staging/.yarnrc
quantlab/staging/index.js
quantlab/staging/package.json
quantlab/staging/webpack.config.js
quantlab/staging/yarn.js
quantlab/staging/build/0.bundle.js
quantlab/staging/build/0.bundle.js.map
quantlab/staging/build/674f50d287a8c48dc19ba404d20fe713.eot
quantlab/staging/build/912ec66d7572ff821749319396470bde.svg
quantlab/staging/build/af7ae505a9eed503f8b8e6982036873e.woff2
quantlab/staging/build/b06871f281fee6b241d60582ae9369b9.ttf
quantlab/staging/build/fee66e712a8a08eef5805a46892932ad.woff
quantlab-0.5.0.dist-info/DESCRIPTION.rst
quantlab-0.5.0.dist-info/METADATA
quantlab-0.5.0.dist-info/RECORD
quantlab-0.5.0.dist-info/WHEEL
quantlab-0.5.0.dist-info/entry_points.txt
quantlab-0.5.0.dist-info/metadata.json
quantlab-0.5.0.dist-info/top_level.txt
