Metadata-Version: 2.0
Name: quantlab
Version: 0.5.0
Summary: An alpha preview of the QuantLab notebook server extension.
Home-page: https://www.quantlab.io
Author: QuantLab Development Team
Author-email: quantlab.io@gmail.com
License: BSD
Keywords: ipython,jupyter,Web,quant
Platform: Linux
Platform: Mac OS X
Platform: Windows
Classifier: Development Status :: 3 - Alpha
Classifier: Intended Audience :: Developers
Classifier: Intended Audience :: System Administrators
Classifier: Intended Audience :: Science/Research
Classifier: License :: OSI Approved :: BSD License
Classifier: Programming Language :: Python
Classifier: Programming Language :: Python :: 2.7
Classifier: Programming Language :: Python :: 3
Classifier: Programming Language :: Python :: 3.4
Classifier: Programming Language :: Python :: 3.5
Classifier: Programming Language :: Python :: 3.6
Requires-Dist: futures
Requires-Dist: ipython-genutils
Requires-Dist: notebook (>=4.3.1)
Requires-Dist: quantlab-launcher (>=0.3.0)
Requires-Dist: subprocess32
Provides-Extra: docs
Requires-Dist: recommonmark; extra == 'docs'
Requires-Dist: sphinx; extra == 'docs'
Requires-Dist: sphinx-rtd-theme; extra == 'docs'
Provides-Extra: test
Requires-Dist: pytest; extra == 'test'
Requires-Dist: pytest-check-links; extra == 'test'
Requires-Dist: requests; extra == 'test'
Requires-Dist: selenium; extra == 'test'
Provides-Extra: test
Requires-Dist: mock; python_version == "2.7" and extra == 'test'
